lavague/exporters/python/__init__.py
lavague/exporters/python/base.py
lavague_exporters_python-0.1.0.dist-info/METADATA
lavague_exporters_python-0.1.0.dist-info/WHEEL
lavague_exporters_python-0.1.0.dist-info/RECORD
